Workbook

Sheet Дашборд
B1: Товаров в матрице : | D1: =COUNTA(Расчет!A2:A11) -> 10 | F1: Средняя чистая прибыль : | H1: =AVERAGE(Расчет!G2:G11) -> 1591.4 | J1: Средний ROI : | L1: =AVERAGE(Расчет!I2:I11) -> 0.98832215 | N1: Лидер по прибыли : | P1: =INDEX(Расчет!A2:A11,MATCH(MAX(Расчет!G2:G11),Расчет!G2:G11,0)) -> Умные очки с камерой с AI | R1: Аутсайдер : | T1: =INDEX(Расчет!A2:A11,MATCH(MIN(Расчет!G2:G11),Расчет!G2:G11,0)) -> Гриндер для когтей собак

Sheet Расчет
A1: Наименование | B1: Арт. | C1: Зак.цена | D1: Роз.цена | E1: Валовая прибыль | F1: Затраты на озон(FBO)/шт | G1: Чистая прибыль | H1: Маржа | I1: ROI | K1: Среднее значение
A2: Гриндер для когтей собак | B2: 3245847975 | C2: 401 | D2: 1082 | E2: =D2-C2 -> 681 | F2: 600 | G2: =E2-F2 -> 81 | H2: =G2/D2 -> 0.074861368 | I2: =G2/C2 -> 0.20199501 | K2: ROI | L2: =AVERAGE(I2:I11) -> 0.98832215
A3: Ароматизатор для автомобиля, автоматический | B3: 1746366524 | C3: 530 | D3: 1337 | E3: =D3-C3 -> 807 | F3: 630 | G3: =E3-F3 -> 177 | H3: =G3/D3 -> 0.13238594 | I3: =G3/C3 -> 0.33396226 | K3: Маржа | L3: =AVERAGE(H2:H11) -> 0.23782697
A4: Маска для плавания с трубкой | B4: 3390573801 | C4: 500 | D4: 1708 | E4: =D4-C4 -> 1208 | F4: 843 | G4: =E4-F4 -> 365 | H4: =G4/D4 -> 0.21370023 | I4: =G4/C4 -> 0.73
A5: Подогреватель для бутылочек портативный | B5: 2830325376 | C5: 616 | D5: 2226 | E5: =D5-C5 -> 1610 | F5: 1229 | G5: =E5-F5 -> 381 | H5: =G5/D5 -> 0.17115903 | I5: =G5/C5 -> 0.61850649 | K5: Данные для матрицы
A6: Видеоняня с монитором IlPro SM650 | B6: 2642588105 | C6: 2200 | D6: 6226 | E6: =D6-C6 -> 4026 | F6: 3159 | G6: =E6-F6 -> 867 | H6: =G6/D6 -> 0.13925474 | I6: =G6/C6 -> 0.39409091 | K6: Маржа | L6: =L3 -> 0.23782697 | M6: 0
A7: Спальный мешок-одеяло с кап. 220х180 см | B7: 1566845960 | C7: 609 | D7: 3161 | E7: =D7-C7 -> 2552 | F7: 1555 | G7: =E7-F7 -> 997 | H7: =G7/D7 -> 0.31540652 | I7: =G7/C7 -> 1.63711 | L7: =L3 -> 0.23782697 | M7: 2.5
A8: Подводная камера для рыбалки | B8: 3074060433 | C8: 1614 | D8: 4774 | E8: =D8-C8 -> 3160 | F8: 2071 | G8: =E8-F8 -> 1089 | H8: =G8/D8 -> 0.2281106 | I8: =G8/C8 -> 0.67472119 | K8: ROI | L8: 0 | M8: =L2 -> 0.98832215
A9: Дрон x30 Pro Max 8K | B9: 2143422498 | C9: 1900 | D9: 8354 | E9: =D9-C9 -> 6454 | F9: 3789 | G9: =E9-F9 -> 2665 | H9: =G9/D9 -> 0.31900886 | I9: =G9/C9 -> 1.4026316 | L9: 1 | M9: =L2 -> 0.98832215
A10: Пароочиститель для уборки дома | B10: 3549857842 | C10: 2685 | D10: 11256 | E10: =D10-C10 -> 8571 | F10: 4510 | G10: =E10-F10 -> 4061 | H10: =G10/D10 -> 0.36078536 | I10: =G10/C10 -> 1.5124767
A11: Умные очки с камерой с AI | B11: 2967583833 | C11: 2200 | D11: 12349 | E11: =D11-C11 -> 10149 | F11: 4918 | G11: =E11-F11 -> 5231 | H11: =G11/D11 -> 0.42359705 | I11: =G11/C11 -> 2.3777273

Sheet Вводные данные
